{
  "meta": { "subject": "english", "grade": "middle", "name": "初中核心词汇（扩充版）", "version": "2024", "count": 150 },
  "cards": [
    { "id": "em_001", "type": "word", "front": "achieve", "back": "实现；取得（v.）", "phonetic": "/əˈtʃiːv/", "hint": "努力后达成目标", "example": "She achieved her dream of becoming a doctor.", "tags": ["动词","初中核心词"] },
    { "id": "em_002", "type": "word", "front": "actually", "back": "实际上；事实上（adv.）", "phonetic": "/ˈæktʃuəli/", "hint": "表示与预期相反", "example": "I actually enjoyed the test.", "tags": ["副词","初中核心词"] },
    { "id": "em_003", "type": "word", "front": "advice", "back": "建议；忠告（n. 不可数）", "phonetic": "/ədˈvaɪs/", "hint": "a piece of advice = 一条建议", "example": "Can you give me some advice?", "tags": ["名词","初中核心词"] },
    { "id": "em_004", "type": "word", "front": "agree", "back": "同意；赞成（v.）", "phonetic": "/əˈɡriː/", "hint": "agree with sb. = 同意某人", "example": "I agree with you completely.", "tags": ["动词","初中核心词"] },
    { "id": "em_005", "type": "word", "front": "although", "back": "虽然；尽管（conj.）", "phonetic": "/ɔːlˈðoʊ/", "hint": "although不能与but连用", "example": "Although it was raining, we went out.", "tags": ["连词","初中核心词"] },
    { "id": "em_006", "type": "word", "front": "amazing", "back": "令人惊奇的；了不起的（adj.）", "phonetic": "/əˈmeɪzɪŋ/", "hint": "让人感到惊叹", "example": "The view was absolutely amazing.", "tags": ["形容词","初中核心词"] },
    { "id": "em_007", "type": "word", "front": "ancient", "back": "古代的；古老的（adj.）", "phonetic": "/ˈeɪnʃənt/", "hint": "ancient history = 古代史", "example": "China has an ancient civilization.", "tags": ["形容词","初中核心词"] },
    { "id": "em_008", "type": "word", "front": "angry", "back": "生气的；愤怒的（adj.）", "phonetic": "/ˈæŋɡri/", "hint": "be angry with sb. = 对某人生气", "example": "Don't be angry with me!", "tags": ["形容词","初中核心词"] },
    { "id": "em_009", "type": "word", "front": "appear", "back": "出现；似乎（v.）", "phonetic": "/əˈpɪr/", "hint": "It appears that... = 似乎...", "example": "Suddenly a rabbit appeared.", "tags": ["动词","初中核心词"] },
    { "id": "em_010", "type": "word", "front": "because of", "back": "因为；由于（介词短语，后接名词）", "phonetic": "/bɪˈkɒz əv/", "hint": "因为+名词用because of", "example": "He was late because of the traffic.", "tags": ["短语","初中核心词"] },
    { "id": "em_011", "type": "word", "front": "believe", "back": "相信；认为（v.）", "phonetic": "/bɪˈliːv/", "hint": "believe in = 信任（某事物存在）", "example": "I believe you can do it.", "tags": ["动词","初中核心词"] },
    { "id": "em_012", "type": "word", "front": "borrow", "back": "借（入）；借用（v.）", "phonetic": "/ˈbɒroʊ/", "hint": "borrow向别人借，lend借给别人", "example": "Can I borrow your pen?", "tags": ["动词","初中核心词"] },
    { "id": "em_013", "type": "word", "front": "careful", "back": "小心的；仔细的（adj.）", "phonetic": "/ˈkerfəl/", "hint": "be careful = 小心！", "example": "Be careful when you cross the street.", "tags": ["形容词","初中核心词"] },
    { "id": "em_014", "type": "word", "front": "compare", "back": "比较；对比（v.）", "phonetic": "/kəmˈper/", "hint": "compare with/to = 与...比较", "example": "Compare your answer with mine.", "tags": ["动词","初中核心词"] },
    { "id": "em_015", "type": "word", "front": "competition", "back": "比赛；竞争（n.）", "phonetic": "/ˌkɒmpəˈtɪʃən/", "hint": "compete → competition", "example": "She won the singing competition.", "tags": ["名词","初中核心词"] },
    { "id": "em_016", "type": "word", "front": "continue", "back": "继续；持续（v.）", "phonetic": "/kənˈtɪnjuː/", "hint": "continue doing/to do", "example": "Please continue with your work.", "tags": ["动词","初中核心词"] },
    { "id": "em_017", "type": "word", "front": "culture", "back": "文化；文明（n.）", "phonetic": "/ˈkʌltʃər/", "hint": "traditional culture = 传统文化", "example": "Chinese culture is very rich.", "tags": ["名词","初中核心词"] },
    { "id": "em_018", "type": "word", "front": "dangerous", "back": "危险的（adj.）", "phonetic": "/ˈdeɪndʒərəs/", "hint": "danger → dangerous", "example": "It's dangerous to swim alone.", "tags": ["形容词","初中核心词"] },
    { "id": "em_019", "type": "word", "front": "decide", "back": "决定；决心（v.）", "phonetic": "/dɪˈsaɪd/", "hint": "decide to do sth. = 决定做某事", "example": "I decided to study harder.", "tags": ["动词","初中核心词"] },
    { "id": "em_020", "type": "word", "front": "develop", "back": "发展；开发（v.）", "phonetic": "/dɪˈveləp/", "hint": "develop skills = 培养技能", "example": "China has developed rapidly.", "tags": ["动词","初中核心词"] },
    { "id": "em_021", "type": "word", "front": "difference", "back": "差异；不同；区别（n.）", "phonetic": "/ˈdɪfrəns/", "hint": "make a difference = 有影响", "example": "Your help makes a big difference.", "tags": ["名词","初中核心词"] },
    { "id": "em_022", "type": "word", "front": "education", "back": "教育；学历（n.）", "phonetic": "/ˌedʒuˈkeɪʃən/", "hint": "educate → education", "example": "Education is very important.", "tags": ["名词","初中核心词"] },
    { "id": "em_023", "type": "word", "front": "environment", "back": "环境；自然环境（n.）", "phonetic": "/ɪnˈvaɪrənmənt/", "hint": "protect the environment = 保护环境", "example": "We must protect our environment.", "tags": ["名词","初中核心词"] },
    { "id": "em_024", "type": "word", "front": "especially", "back": "尤其；特别（adv.）", "phonetic": "/ɪˈspeʃəli/", "hint": "用于强调", "example": "I love sports, especially basketball.", "tags": ["副词","初中核心词"] },
    { "id": "em_025", "type": "word", "front": "except", "back": "除...以外（不包括）（prep.）", "phonetic": "/ɪkˈsept/", "hint": "except=不包括，besides=包括（另外）", "example": "Everyone passed except Tom.", "tags": ["介词","初中核心词"] },
    { "id": "em_026", "type": "word", "front": "experience", "back": "经历；经验（n.）", "phonetic": "/ɪkˈspɪriəns/", "hint": "可数=一次经历；不可数=经验", "example": "That was an amazing experience.", "tags": ["名词","初中核心词"] },
    { "id": "em_027", "type": "word", "front": "explain", "back": "解释；说明（v.）", "phonetic": "/ɪkˈspleɪn/", "hint": "explain sth. to sb.", "example": "Please explain the rule to us.", "tags": ["动词","初中核心词"] },
    { "id": "em_028", "type": "word", "front": "fail", "back": "失败；不及格（v.）", "phonetic": "/feɪl/", "hint": "fail to do = 未能做成", "example": "Don't be afraid to fail.", "tags": ["动词","初中核心词"] },
    { "id": "em_029", "type": "word", "front": "foreign", "back": "外国的；异国的（adj.）", "phonetic": "/ˈfɔːrən/", "hint": "foreign country = 外国", "example": "She speaks three foreign languages.", "tags": ["形容词","初中核心词"] },
    { "id": "em_030", "type": "word", "front": "friendly", "back": "友好的；亲切的（adj.）", "phonetic": "/ˈfrendli/", "hint": "be friendly to sb. = 对某人友好", "example": "Everyone here is very friendly.", "tags": ["形容词","初中核心词"] },
    { "id": "em_031", "type": "word", "front": "habit", "back": "习惯；癖好（n.）", "phonetic": "/ˈhæbɪt/", "hint": "good/bad habit = 好/坏习惯", "example": "Exercise is a good habit.", "tags": ["名词","初中核心词"] },
    { "id": "em_032", "type": "word", "front": "however", "back": "然而；但是（conj./adv.）", "phonetic": "/haʊˈevər/", "hint": "表示转折，常在句中用逗号隔开", "example": "I wanted to go. However, it rained.", "tags": ["连词","初中核心词"] },
    { "id": "em_033", "type": "word", "front": "imagine", "back": "想象；设想（v.）", "phonetic": "/ɪˈmædʒɪn/", "hint": "imagine doing = 想象做某事", "example": "Imagine living on the moon!", "tags": ["动词","初中核心词"] },
    { "id": "em_034", "type": "word", "front": "important", "back": "重要的；重大的（adj.）", "phonetic": "/ɪmˈpɔːrtənt/", "hint": "it is important to do = 做...很重要", "example": "It is important to be honest.", "tags": ["形容词","初中核心词"] },
    { "id": "em_035", "type": "word", "front": "introduce", "back": "介绍；引进（v.）", "phonetic": "/ˌɪntrəˈdjuːs/", "hint": "introduce sb. to sb. = 把某人介绍给某人", "example": "Let me introduce my friend to you.", "tags": ["动词","初中核心词"] },
    { "id": "em_036", "type": "word", "front": "invent", "back": "发明；创造（v.）", "phonetic": "/ɪnˈvent/", "hint": "invent=发明原来没有的；discover=发现已存在的", "example": "Edison invented the light bulb.", "tags": ["动词","初中核心词"] },
    { "id": "em_037", "type": "word", "front": "journey", "back": "旅行；旅程（n.）", "phonetic": "/ˈdʒɜːrni/", "hint": "journey通常指陆上较长的旅行", "example": "The journey took three hours.", "tags": ["名词","初中核心词"] },
    { "id": "em_038", "type": "word", "front": "knowledge", "back": "知识；学问（n. 不可数）", "phonetic": "/ˈnɒlɪdʒ/", "hint": "a piece of knowledge", "example": "Knowledge is power.", "tags": ["名词","初中核心词"] },
    { "id": "em_039", "type": "word", "front": "lifestyle", "back": "生活方式（n.）", "phonetic": "/ˈlaɪfstaɪl/", "hint": "healthy lifestyle = 健康的生活方式", "example": "Exercise leads to a healthy lifestyle.", "tags": ["名词","初中核心词"] },
    { "id": "em_040", "type": "word", "front": "lucky", "back": "幸运的（adj.）", "phonetic": "/ˈlʌki/", "hint": "be lucky to do = 幸运地做", "example": "I'm lucky to have good friends.", "tags": ["形容词","初中核心词"] },
    { "id": "em_041", "type": "word", "front": "matter", "back": "事情；要紧（n./v.）", "phonetic": "/ˈmætər/", "hint": "What's the matter? = 怎么了？", "example": "It doesn't matter. = 没关系", "tags": ["名词/动词","初中核心词"] },
    { "id": "em_042", "type": "word", "front": "message", "back": "信息；消息；留言（n.）", "phonetic": "/ˈmesɪdʒ/", "hint": "leave a message = 留言", "example": "Can I leave a message for her?", "tags": ["名词","初中核心词"] },
    { "id": "em_043", "type": "word", "front": "nation", "back": "国家；民族（n.）", "phonetic": "/ˈneɪʃən/", "hint": "national = 国家的（形容词）", "example": "China is a great nation.", "tags": ["名词","初中核心词"] },
    { "id": "em_044", "type": "word", "front": "necessary", "back": "必要的；必需的（adj.）", "phonetic": "/ˈnesəseri/", "hint": "It is necessary to do = 有必要做", "example": "It's necessary to review daily.", "tags": ["形容词","初中核心词"] },
    { "id": "em_045", "type": "word", "front": "nervous", "back": "紧张的；焦虑的（adj.）", "phonetic": "/ˈnɜːrvəs/", "hint": "be nervous about = 对...感到紧张", "example": "I'm nervous about the exam.", "tags": ["形容词","初中核心词"] },
    { "id": "em_046", "type": "word", "front": "opportunity", "back": "机会；时机（n.）", "phonetic": "/ˌɒpəˈtjuːnɪti/", "hint": "have an opportunity to do = 有机会做", "example": "This is a great opportunity.", "tags": ["名词","初中核心词"] },
    { "id": "em_047", "type": "word", "front": "organize", "back": "组织；安排；整理（v.）", "phonetic": "/ˈɔːrɡənaɪz/", "hint": "organize an event = 组织活动", "example": "Let's organize a class party.", "tags": ["动词","初中核心词"] },
    { "id": "em_048", "type": "word", "front": "opinion", "back": "意见；观点（n.）", "phonetic": "/əˈpɪnjən/", "hint": "In my opinion = 在我看来", "example": "In my opinion, we should try harder.", "tags": ["名词","初中核心词"] },
    { "id": "em_049", "type": "word", "front": "particular", "back": "特别的；特殊的（adj.）", "phonetic": "/pəˈtɪkjələr/", "hint": "in particular = 尤其；特别", "example": "I like this one in particular.", "tags": ["形容词","初中核心词"] },
    { "id": "em_050", "type": "word", "front": "perhaps", "back": "也许；可能（adv.）", "phonetic": "/pəˈhæps/", "hint": "=maybe，表示不确定", "example": "Perhaps she will come tomorrow.", "tags": ["副词","初中核心词"] },
    { "id": "em_051", "type": "word", "front": "plenty", "back": "大量；丰富（n./adv.）", "phonetic": "/ˈplenti/", "hint": "plenty of = 大量（修饰可数和不可数均可）", "example": "There is plenty of food for everyone.", "tags": ["名词","初中核心词"] },
    { "id": "em_052", "type": "word", "front": "polite", "back": "礼貌的；有礼貌的（adj.）", "phonetic": "/pəˈlaɪt/", "hint": "be polite to sb. = 对某人礼貌", "example": "It's polite to say please and thank you.", "tags": ["形容词","初中核心词"] },
    { "id": "em_053", "type": "word", "front": "population", "back": "人口；种群数量（n.）", "phonetic": "/ˌpɒpjuˈleɪʃən/", "hint": "China has a large population.", "example": "The world population is over 8 billion.", "tags": ["名词","初中核心词"] },
    { "id": "em_054", "type": "word", "front": "possible", "back": "可能的；做得到的（adj.）", "phonetic": "/ˈpɒsɪbəl/", "hint": "as...as possible = 尽可能...", "example": "Please reply as soon as possible.", "tags": ["形容词","初中核心词"] },
    { "id": "em_055", "type": "word", "front": "prepare", "back": "准备；预备（v.）", "phonetic": "/prɪˈper/", "hint": "prepare for = 为...做准备", "example": "We need to prepare for the exam.", "tags": ["动词","初中核心词"] },
    { "id": "em_056", "type": "word", "front": "prevent", "back": "阻止；预防（v.）", "phonetic": "/prɪˈvent/", "hint": "prevent sb. from doing = 阻止某人做", "example": "Exercise can prevent illness.", "tags": ["动词","初中核心词"] },
    { "id": "em_057", "type": "word", "front": "produce", "back": "生产；制造（v.）", "phonetic": "/prəˈdjuːs/", "hint": "produce energy = 产生能量", "example": "This factory produces cars.", "tags": ["动词","初中核心词"] },
    { "id": "em_058", "type": "word", "front": "protect", "back": "保护；防护（v.）", "phonetic": "/prəˈtekt/", "hint": "protect the environment = 保护环境", "example": "We should protect endangered animals.", "tags": ["动词","初中核心词"] },
    { "id": "em_059", "type": "word", "front": "proud", "back": "自豪的；骄傲的（adj.）", "phonetic": "/praʊd/", "hint": "be proud of = 为...感到骄傲", "example": "I'm proud of my country.", "tags": ["形容词","初中核心词"] },
    { "id": "em_060", "type": "word", "front": "raise", "back": "举起；提高；养育（v.）", "phonetic": "/reɪz/", "hint": "raise money = 筹钱；raise children = 养育孩子", "example": "She raised her hand to answer.", "tags": ["动词","初中核心词"] },
    { "id": "em_061", "type": "word", "front": "realize", "back": "意识到；实现（v.）", "phonetic": "/ˈrɪəlaɪz/", "hint": "realize = 认识到（常接 that 从句）", "example": "I didn't realize how late it was.", "tags": ["动词","初中核心词"] },
    { "id": "em_062", "type": "word", "front": "recent", "back": "最近的；近来的（adj.）", "phonetic": "/ˈriːsənt/", "hint": "recently = 最近（副词）", "example": "In recent years, technology has improved.", "tags": ["形容词","初中核心词"] },
    { "id": "em_063", "type": "word", "front": "refuse", "back": "拒绝；不愿意（v.）", "phonetic": "/rɪˈfjuːz/", "hint": "refuse to do = 拒绝做某事", "example": "He refused to give up.", "tags": ["动词","初中核心词"] },
    { "id": "em_064", "type": "word", "front": "respect", "back": "尊重；敬意（n./v.）", "phonetic": "/rɪˈspekt/", "hint": "show respect = 表示尊重", "example": "We should respect our teachers.", "tags": ["名词/动词","初中核心词"] },
    { "id": "em_065", "type": "word", "front": "result", "back": "结果；成绩（n.）", "phonetic": "/rɪˈzʌlt/", "hint": "as a result = 结果（常用短语）", "example": "As a result, he passed the test.", "tags": ["名词","初中核心词"] },
    { "id": "em_066", "type": "word", "front": "seem", "back": "似乎；看来（v.）", "phonetic": "/siːm/", "hint": "seem to do / seem + adj = 看起来...", "example": "She seems to be happy today.", "tags": ["动词","初中核心词"] },
    { "id": "em_067", "type": "word", "front": "serious", "back": "严肃的；认真的；严重的（adj.）", "phonetic": "/ˈsɪəriəs/", "hint": "seriously = 严重地；be serious about = 认真对待", "example": "This is a serious problem.", "tags": ["形容词","初中核心词"] },
    { "id": "em_068", "type": "word", "front": "share", "back": "分享；共用（v.）", "phonetic": "/ʃer/", "hint": "share sth. with sb. = 与某人分享", "example": "Please share your ideas with us.", "tags": ["动词","初中核心词"] },
    { "id": "em_069", "type": "word", "front": "solve", "back": "解决；解答（v.）", "phonetic": "/sɒlv/", "hint": "solve a problem = 解决问题", "example": "We need to solve this problem together.", "tags": ["动词","初中核心词"] },
    { "id": "em_070", "type": "word", "front": "succeed", "back": "成功；达到目的（v.）", "phonetic": "/səkˈsiːd/", "hint": "succeed in doing = 成功地做了", "example": "Hard work helps you succeed.", "tags": ["动词","初中核心词"] },
    { "id": "em_071", "type": "word", "front": "suggest", "back": "建议；暗示（v.）", "phonetic": "/səˈdʒest/", "hint": "suggest doing（不是to do）", "example": "I suggest trying a different approach.", "tags": ["动词","初中核心词"] },
    { "id": "em_072", "type": "word", "front": "support", "back": "支持；支撑（v./n.）", "phonetic": "/səˈpɔːrt/", "hint": "support sb. = 支持某人", "example": "Thank you for your support.", "tags": ["动词/名词","初中核心词"] },
    { "id": "em_073", "type": "word", "front": "surprised", "back": "感到吃惊的（adj.）", "phonetic": "/səˈpraɪzd/", "hint": "be surprised at/by = 对...感到吃惊", "example": "I was surprised by the news.", "tags": ["形容词","初中核心词"] },
    { "id": "em_074", "type": "word", "front": "technology", "back": "技术；科技（n.）", "phonetic": "/tekˈnɒlədʒi/", "hint": "information technology = IT", "example": "Technology has changed our lives.", "tags": ["名词","初中核心词"] },
    { "id": "em_075", "type": "word", "front": "themselves", "back": "他们自己（pron. 反身代词）", "phonetic": "/ðəmˈselvz/", "hint": "they → themselves（反身代词）", "example": "They can do it themselves.", "tags": ["代词","初中核心词"] },
    { "id": "em_076", "type": "word", "front": "therefore", "back": "因此；所以（adv.）", "phonetic": "/ˈðerəfɔːr/", "hint": "表示因果结论，比so更正式", "example": "He studied hard; therefore, he passed.", "tags": ["副词","初中核心词"] },
    { "id": "em_077", "type": "word", "front": "though", "back": "虽然；即使；不过（conj./adv.）", "phonetic": "/ðoʊ/", "hint": "= although（口语中更常用）", "example": "He's tired, though he won't stop.", "tags": ["连词","初中核心词"] },
    { "id": "em_078", "type": "word", "front": "throughout", "back": "遍及；自始至终（prep./adv.）", "phonetic": "/θruːˈaʊt/", "hint": "throughout the world = 全世界", "example": "It rained throughout the day.", "tags": ["介词","初中核心词"] },
    { "id": "em_079", "type": "word", "front": "traditional", "back": "传统的；惯例的（adj.）", "phonetic": "/trəˈdɪʃənl/", "hint": "tradition(n.) → traditional(adj.)", "example": "We enjoy traditional Chinese food.", "tags": ["形容词","初中核心词"] },
    { "id": "em_080", "type": "word", "front": "trouble", "back": "麻烦；困难；烦恼（n.）", "phonetic": "/ˈtrʌbəl/", "hint": "have trouble doing = 做...有困难", "example": "He's in trouble with his homework.", "tags": ["名词","初中核心词"] },
    { "id": "em_081", "type": "word", "front": "understand", "back": "理解；明白（v.）", "phonetic": "/ˌʌndəˈstænd/", "hint": "Do you understand? = 你明白了吗？", "example": "I don't understand this question.", "tags": ["动词","初中核心词"] },
    { "id": "em_082", "type": "word", "front": "unique", "back": "独特的；唯一的（adj.）", "phonetic": "/juˈniːk/", "hint": "unique to = 是...所特有的", "example": "Each person is unique.", "tags": ["形容词","初中核心词"] },
    { "id": "em_083", "type": "word", "front": "unless", "back": "除非；如果不（conj.）", "phonetic": "/ənˈles/", "hint": "unless = if not", "example": "I won't go unless you come.", "tags": ["连词","初中核心词"] },
    { "id": "em_084", "type": "word", "front": "various", "back": "各种各样的；不同的（adj.）", "phonetic": "/ˈveəriəs/", "hint": "various = many different kinds of", "example": "There are various ways to solve it.", "tags": ["形容词","初中核心词"] },
    { "id": "em_085", "type": "word", "front": "volunteer", "back": "志愿者；自愿（n./v.）", "phonetic": "/ˌvɒlənˈtɪər/", "hint": "volunteer work = 志愿工作", "example": "I volunteer at the local library.", "tags": ["名词/动词","初中核心词"] },
    { "id": "em_086", "type": "word", "front": "waste", "back": "浪费；废料（n./v.）", "phonetic": "/weɪst/", "hint": "waste time = 浪费时间", "example": "Don't waste water.", "tags": ["动词/名词","初中核心词"] },
    { "id": "em_087", "type": "word", "front": "whether", "back": "是否；不管（conj.）", "phonetic": "/ˈweðər/", "hint": "whether...or not = 不管...还是不", "example": "I don't know whether she will come.", "tags": ["连词","初中核心词"] },
    { "id": "em_088", "type": "word", "front": "whole", "back": "整个的；全部的（adj.）", "phonetic": "/hoʊl/", "hint": "the whole day = 整整一天", "example": "I spent the whole day studying.", "tags": ["形容词","初中核心词"] },
    { "id": "em_089", "type": "word", "front": "worth", "back": "值得；有...的价值（prep./adj.）", "phonetic": "/wɜːrθ/", "hint": "be worth doing = 值得做", "example": "This book is worth reading.", "tags": ["形容词","初中核心词"] },
    { "id": "em_090", "type": "word", "front": "choice", "back": "选择；所选之物（n.）", "phonetic": "/tʃɔɪs/", "hint": "make a choice = 做出选择", "example": "You have to make a choice.", "tags": ["名词","初中核心词"] },
    { "id": "em_091", "type": "word", "front": "concentrate", "back": "集中；专心（v.）", "phonetic": "/ˈkɒnsəntreɪt/", "hint": "concentrate on = 专注于", "example": "Concentrate on your studies.", "tags": ["动词","初中核心词"] },
    { "id": "em_092", "type": "word", "front": "consider", "back": "考虑；认为（v.）", "phonetic": "/kənˈsɪdər/", "hint": "consider doing sth.", "example": "Have you considered changing jobs?", "tags": ["动词","初中核心词"] },
    { "id": "em_093", "type": "word", "front": "contain", "back": "包含；容纳（v.）", "phonetic": "/kənˈteɪn/", "hint": "The box contains books.", "example": "Oranges contain vitamin C.", "tags": ["动词","初中核心词"] },
    { "id": "em_094", "type": "word", "front": "deal", "back": "处理；交易（v./n.）", "phonetic": "/diːl/", "hint": "deal with = 处理；a great deal of = 大量", "example": "How do you deal with stress?", "tags": ["动词/名词","初中核心词"] },
    { "id": "em_095", "type": "word", "front": "effect", "back": "效果；影响（n.）", "phonetic": "/ɪˈfekt/", "hint": "have an effect on = 对...有影响；区分affect(v.)和effect(n.)", "example": "Exercise has a positive effect on health.", "tags": ["名词","初中核心词"] },
    { "id": "em_096", "type": "word", "front": "expect", "back": "期待；预计（v.）", "phonetic": "/ɪkˈspekt/", "hint": "expect sb. to do = 期待某人做", "example": "I expect to pass the exam.", "tags": ["动词","初中核心词"] },
    { "id": "em_097", "type": "word", "front": "express", "back": "表达；表示（v.）", "phonetic": "/ɪkˈspres/", "hint": "express one's feelings = 表达感情", "example": "It's important to express yourself.", "tags": ["动词","初中核心词"] },
    { "id": "em_098", "type": "word", "front": "focus", "back": "集中（v.）；焦点（n.）", "phonetic": "/ˈfoʊkəs/", "hint": "focus on = 专注于", "example": "Focus on the most important things.", "tags": ["动词/名词","初中核心词"] },
    { "id": "em_099", "type": "word", "front": "force", "back": "强迫；力量（v./n.）", "phonetic": "/fɔːrs/", "hint": "force sb. to do = 强迫某人做", "example": "Don't force yourself too hard.", "tags": ["动词/名词","初中核心词"] },
    { "id": "em_100", "type": "word", "front": "goal", "back": "目标；球门（n.）", "phonetic": "/ɡoʊl/", "hint": "set a goal = 设定目标", "example": "My goal is to learn English well.", "tags": ["名词","初中核心词"] }
  ]
}
